<?xml version="1.0" encoding="UTF-8"?>
<dictionary title="country6">
 <desc>Created from SPARQL query</desc>
 <entry _p297_country="AF" description="sovereign state situated at the confluence of Western, Central, and South Asia" name="Afghanistan" term="Afghanistan" wikidataURL="http://www.wikidata.org/entity/Q889" wikipediaPage="https://en.wikipedia.org/wiki/Afghanistan" wikipediaURL="https://en.wikipedia.org/wiki/Afghanistan" wikidataID="Q889">
  <synonym>AFG</synonym>
  <synonym>af</synonym>
  <synonym>Islamic Republic of Afghanistan</synonym>
 </entry>
 <entry _p297_country="AL" description="sovereign state in Southeast Europe" name="Albania" wikidataID="Q222" term="Albania" wikidataURL="http://www.wikidata.org/entity/Q222" wikipediaPage="https://en.wikipedia.org/wiki/Albania" wikipediaURL="https://en.wikipedia.org/wiki/Albania" >
  <synonym>ALB</synonym>
  <synonym>al</synonym>
  <synonym>Republic of Albania</synonym>
  <synonym>Republika e Shqipërisë</synonym>
  <synonym>Shqipërisë</synonym>
 </entry>
 <entry _p297_country="DZ" description="sovereign state in North Africa" name="Algeria" term="Algeria" wikidataURL="http://www.wikidata.org/entity/Q262" wikipediaPage="https://en.wikipedia.org/wiki/Algeria" wikipediaURL="https://en.wikipedia.org/wiki/Algeria" wikidataID="Q262">
  <synonym>ALG</synonym>
  <synonym>dz</synonym>
  <synonym>People's Democratic Republic of Algeria</synonym>
 </entry>
 <entry _p297_country="AS" description="US territory in the Pacific" name="American Samoa" term="American Samoa" wikidataURL="http://www.wikidata.org/entity/Q16641" wikipediaPage="https://en.wikipedia.org/wiki/American_Samoa" wikipediaURL="https://en.wikipedia.org/wiki/American_Samoa" wikidataID="Q16641">
  <synonym>ASA</synonym>
  <synonym>as</synonym>
  <synonym>East Samoa</synonym>
  <synonym>Samoa (American)</synonym>
  <synonym>Territory of American Samoa</synonym>
  <synonym>U.S. Samoa</synonym>
  <synonym>US Samoa</synonym>
 </entry>
 <entry _p297_country="AD" description="sovereign microstate between France and Spain, in Western Europe" name="Andorra" term="Andorra" wikidataURL="http://www.wikidata.org/entity/Q228" wikipediaPage="https://en.wikipedia.org/wiki/Andorra" wikipediaURL="https://en.wikipedia.org/wiki/Andorra" wikidataID="Q228">
  <synonym>AND</synonym>
  <synonym>ad</synonym>
  <synonym>Principality of Andorra</synonym>
  <synonym>Principality of the Valleys of Andorra</synonym>
 </entry>
 <entry _p297_country="AO" description="sovereign state in Africa" name="Angola" term="Angola" wikidataURL="http://www.wikidata.org/entity/Q916" wikipediaPage="https://en.wikipedia.org/wiki/Angola" wikipediaURL="https://en.wikipedia.org/wiki/Angola" wikidataID="Q916">
  <synonym>ANG</synonym>
  <synonym>ao</synonym>
  <synonym>Ngola</synonym>
  <synonym>Republic of Angola</synonym>
 </entry>
 <entry _p297_country="AI" description="British Overseas Territory in the Caribbean" name="Anguilla" term="Anguilla" wikidataURL="http://www.wikidata.org/entity/Q25228" wikipediaPage="https://en.wikipedia.org/wiki/Anguilla" wikipediaURL="https://en.wikipedia.org/wiki/Anguilla" wikidataID="Q25228">
  <synonym>ai</synonym>
 </entry>
</dictionary>