<?xml version="1.0" encoding="UTF-8"?>
<fig id="Fig1">
 <label>Fig. 1</label>
 <caption>
  <p>Scintigraphic images obtained immediately after AO (
   <bold>a</bold>) and LS (
   <bold>b</bold>) injection of radiolabeled ASCs. The focal round area of intense radioactive signal are external markers placed on the second cervical vertebra (C2), the eighteenth thoracic vertebra (T18), and the third sacral vertebra (S3). The bottom row shows fusion of the scintigraphic images with radiographs after AO (
   <bold>c</bold>) and LS (
   <bold>d</bold>) injection to help with anatomical localization of the ASCs
  </p>
 </caption>
 <graphic xlink:href="13287_2018_849_Fig1_HTML" id="MO1" xmlns:xlink="http://www.w3.org/1999/xlink"/>
</fig>
