<?xml version="1.0" encoding="UTF-8"?>
<supplementary-material content-type="local-data" id="bjh15459-sup-0001">
 <caption>
  <p>
   <bold>Table SI.</bold> Additional baseline demographics of the QoL population for the patients in the intensive and non‐intensive pathways.
  </p>
  <p>
   <bold>Table SII.</bold> Baseline demographics of the QoL population for patients in the maintenance phase.
  </p>
  <p>
   <bold>Fig S1.</bold> Remaining descriptive plots for the three analysis populations. Intensive (A) non‐intensive (B) and maintenance (C). These graphs present the mean subscale scores and approximate 95% confidence intervals at each time point by the variable of interest for complete case data.
  </p>
 </caption>
 <media xlink:href="BJH-182-816-s001.docx" xmlns:xlink="http://www.w3.org/1999/xlink">
  <caption>
   <p>Click here for additional data file.</p>
  </caption>
 </media>
</supplementary-material>
