<?xml version="1.0" encoding="UTF-8"?>
<fig id="f0001" fig-type="figure" orientation="portrait" position="float">
 <label>Figure 1</label>
 <caption>
  <p>The first layer of the reconstruction of the posterior wall of total urethral reconstruction of “Sandwich”. (
   <bold>A</bold>) The structural location of the medial dorsal raphe (MDR) during the operation. (
   <bold>B</bold>) The structural location of the severed end of Denonvillier’s fascia. (
   <bold>C</bold>) The severed Denonvillier’s fascia was sutured with MDR.
  </p>
 </caption>
 <graphic content-type="print-only" xlink:href="CMAR-13-2341-g0001" xmlns:xlink="http://www.w3.org/1999/xlink"/>
</fig>
