<?xml version="1.0" encoding="UTF-8"?>
<ack id="jcsm12316-sec-0024">
 <title>Acknowledgements</title>
 <p>We thank Anne Zergiebel for her excellent coordination work; Gabriela Korus for her great assistance in histology; Shaul Kadosh for the statistical analysis; Cordula Giesler, Annett Sefrin, Maik Stein, and Anke Jurisch for organizing and performing the biomarker tests; and Mark Tastan for assistance with the functional assessments.</p>
 <p>The study was funded by the sponsors Pluristem Therapeutics, the Israeli Innovation Authority, and the German Federal Ministry of Education and Research. The work presented in this article has been the basis of the funding of the HIPGEN project by the European Commission. European Union's Horizon 2020 research and innovation programme under grant agreement No 779293.</p>
 <p>The authors certify that they comply with the ethical guidelines for authorship and publishing of the Journal of Cachexia, Sarcopenia, and Muscle.
  <xref rid="jcsm12316-bib-0041" ref-type="ref">41</xref>
 </p>
</ack>
