<?xml version="1.0" encoding="UTF-8"?>
<fig fig-type="Figure" xml:lang="en" id="cam41690-fig-0003" orientation="portrait" position="float">
 <label>Figure 3</label>
 <caption>
  <p>Mean ± Standard Deviation of 
   <styled-content style="fixed-case">CS</styled-content> obtained from the bed Daysimeters values included are from the hours when the lighting intervention was programmed to be energized. As hypothesized, there was a significant difference in 
   <styled-content style="fixed-case">CS</styled-content> values received in the morning between the two groups
  </p>
 </caption>
 <graphic id="nlm-graphic-7" xlink:href="CAM4-7-4345-g003" xmlns:xlink="http://www.w3.org/1999/xlink"/>
</fig>
