<?xml version="1.0" encoding="UTF-8"?>
<ref id="ref7">
 <mixed-citation publication-type="other">
  <person-group person-group-type="author">
   <collab id="coll2">Deloitte</collab>
  </person-group> (
  <year>2019</year>). 
  <italic>Mobile Consumer Survey 2019: The Australian Cut</italic>. Available at: 
  <ext-link ext-link-type="uri" xlink:href="https://content.deloitte.com.au/mobile-consumer-survey-2019" xmlns:xlink="http://www.w3.org/1999/xlink">https://content.deloitte.com.au/mobile-consumer-survey-2019</ext-link> (Accessed October 5, 2020).
 </mixed-citation>
</ref>
